pc4g/__init__.py
pc4g/api_client.py
pc4g/configuration.py
pc4g/rest.py
pc4g/api/__init__.py
pc4g/api/admin_api.py
pc4g/api/alpha_api.py
pc4g/api/customers_api.py
pc4g/api/locations_api.py
pc4g/api/logs_api.py
pc4g/api/me_api.py
pc4g/api/utilities_api.py
pc4g/models/__init__.py
pc4g/models/account_consumption_model.py
pc4g/models/account_consumption_model_cloudspaces.py
pc4g/models/account_consumption_model_cloudspaces_consumption.py
pc4g/models/account_consumption_model_cloudspaces_vms.py
pc4g/models/account_consumption_model_cloudspaces_vms_consumption.py
pc4g/models/account_consumption_model_consumption.py
pc4g/models/account_consumption_model_objectspaces.py
pc4g/models/account_consumption_model_objectspaces_consumption.py
pc4g/models/account_consumption_model_unassigned_disks.py
pc4g/models/account_consumption_model_unassigned_disks_consumption.py
pc4g/models/account_consumption_ts_model.py
pc4g/models/account_consumption_ts_model_cloudspaces.py
pc4g/models/account_consumption_ts_model_cloudspaces_consumption.py
pc4g/models/account_consumption_ts_model_cloudspaces_consumption_data.py
pc4g/models/account_consumption_ts_model_cloudspaces_vms.py
pc4g/models/account_consumption_ts_model_cloudspaces_vms_consumption.py
pc4g/models/account_consumption_ts_model_cloudspaces_vms_consumption_data.py
pc4g/models/account_consumption_ts_model_consumption.py
pc4g/models/account_consumption_ts_model_consumption_data.py
pc4g/models/account_consumption_ts_model_objectspaces.py
pc4g/models/account_consumption_ts_model_objectspaces_buckets.py
pc4g/models/account_consumption_ts_model_objectspaces_buckets_consumption.py
pc4g/models/account_consumption_ts_model_objectspaces_buckets_consumption_data.py
pc4g/models/account_consumption_ts_model_objectspaces_consumption.py
pc4g/models/account_consumption_ts_model_objectspaces_consumption_data.py
pc4g/models/account_consumption_ts_model_unassigned_disks.py
pc4g/models/account_consumption_ts_model_unassigned_disks_consumption.py
pc4g-1.0.0.dist-info/LICENSE
pc4g-1.0.0.dist-info/METADATA
pc4g-1.0.0.dist-info/WHEEL
pc4g-1.0.0.dist-info/top_level.txt
pc4g-1.0.0.dist-info/RECORD
