Metadata-Version: 2.1
Name: pc4g
Version: 1.0.0
Summary: Python client for GIG based clouds (pc4g)
Home-page: 
Author-email: 
Keywords: Swagger,Python client for GIG based clouds (pc4g)
License-File: LICENSE
Requires-Dist: certifi (>=2017.4.17)
Requires-Dist: python-dateutil (>=2.1)
Requires-Dist: six (>=1.10)
Requires-Dist: urllib3 (>=1.23)
